Metadata-Version: 2.1
Name: ElasticMockaki
Version: 2.0.0
Summary: Python Elasticsearch Mock for test purposes
Home-page: https://github.com/amir_ashy/elasticmock
Author: amir_ashy
Author-email: vrcmarcos@gmail.com
License: UNKNOWN
Platform: UNKNOWN
Classifier: Environment :: Web Environment
Classifier: Intended Audience :: Developers
Classifier: Operating System :: OS Independent
Classifier: Programming Language :: Python
Classifier: Programming Language :: Python :: 3
Classifier: Programming Language :: Python :: 3.6
Classifier: Programming Language :: Python :: 3.7
Classifier: Programming Language :: Python :: 3.8
Classifier: Programming Language :: Python :: 3.9
Classifier: License :: OSI Approved :: MIT License
Classifier: Topic :: Software Development :: Libraries :: Python Modules
License-File: LICENSE
